MySQLdb/__init__.py
MySQLdb/_exceptions.py
MySQLdb/_mysql.c
MySQLdb/_mysql.pypy38-pp73-win_amd64.pyd
MySQLdb/connections.py
MySQLdb/converters.py
MySQLdb/cursors.py
MySQLdb/release.py
MySQLdb/times.py
MySQLdb/constants/CLIENT.py
MySQLdb/constants/CR.py
MySQLdb/constants/ER.py
MySQLdb/constants/FIELD_TYPE.py
MySQLdb/constants/FLAG.py
MySQLdb/constants/__init__.py
mysqlclient-2.2.3.dist-info/LICENSE
mysqlclient-2.2.3.dist-info/METADATA
mysqlclient-2.2.3.dist-info/WHEEL
mysqlclient-2.2.3.dist-info/top_level.txt
mysqlclient-2.2.3.dist-info/RECORD
